projectx_sdk/__init__.py
projectx_sdk/auth.py
projectx_sdk/client.py
projectx_sdk/exceptions.py
projectx_sdk/endpoints/__init__.py
projectx_sdk/endpoints/account.py
projectx_sdk/endpoints/contract.py
projectx_sdk/endpoints/history.py
projectx_sdk/endpoints/order.py
projectx_sdk/endpoints/position.py
projectx_sdk/endpoints/trade.py
projectx_sdk/models/__init__.py
projectx_sdk/models/account.py
projectx_sdk/models/base.py
projectx_sdk/models/contract.py
projectx_sdk/models/history.py
projectx_sdk/models/order.py
projectx_sdk/models/position.py
projectx_sdk/models/trade.py
projectx_sdk/realtime/__init__.py
projectx_sdk/realtime/connection.py
projectx_sdk/realtime/market_hub.py
projectx_sdk/realtime/user_hub.py
projectx_sdk/utils/__init__.py
projectx_sdk/utils/constants.py
projectx_sdk/utils/validators.py
projectx_sdk-0.2.39.dist-info/licenses/LICENSE
projectx_sdk-0.2.39.dist-info/METADATA
projectx_sdk-0.2.39.dist-info/WHEEL
projectx_sdk-0.2.39.dist-info/top_level.txt
projectx_sdk-0.2.39.dist-info/RECORD
